mapster/__init__.py
mapster/__main__.py
mapster/tools.py
mapster-0.3.0.data/data/README.md
mapster-0.3.0.dist-info/LICENSE.txt
mapster-0.3.0.dist-info/METADATA
mapster-0.3.0.dist-info/WHEEL
mapster-0.3.0.dist-info/entry_points.txt
mapster-0.3.0.dist-info/top_level.txt
mapster-0.3.0.dist-info/RECORD
