Metadata-Version: 2.1
Name: mapster
Version: 0.3.0
Summary: An administration tools for maps repository at http://mapywig.org/
Home-page: https://github.com/jedrus2000/mapster
Author: Andrzej Bargański
Author-email: a.barganski@gmail.com
License: MIT
Project-URL: Source, https://github.com/jedrus2000/mapster
Keywords: mapster mapywig cli
Platform: UNKNOWN
Classifier: Environment :: No Input/Output (Daemon)
Classifier: Intended Audience :: End Users/Desktop
Classifier: Topic :: Utilities
Classifier: License :: OSI Approved :: MIT License
Classifier: Programming Language :: Python :: 3.6
Requires-Python: >=3.6
Requires-Dist: setuptools
Requires-Dist: Click (>=7.0)
Requires-Dist: toml (>=0.10.0)
Requires-Dist: requests (>=2.22.0)
Requires-Dist: colorama (>=0.4.3)
Provides-Extra: dev
Requires-Dist: twine ; extra == 'dev'
Requires-Dist: wheel ; extra == 'dev'
